qsync_control/__init__.py
qsync_control-2.0.1.dist-info/LICENSE
qsync_control-2.0.1.dist-info/METADATA
qsync_control-2.0.1.dist-info/WHEEL
qsync_control-2.0.1.dist-info/top_level.txt
qsync_control-2.0.1.dist-info/RECORD
