Metadata-Version: 2.1
Name: qsync-control
Version: 2.0.1
Summary: Python library for operating QMotion blinds controlled a QSync device.
Home-page: https://github.com/exitexit/qsync-control
Author: Tao Xie
Author-email: taoxie@alumni.unc.edu
License: UNKNOWN
Platform: UNKNOWN
Classifier: Programming Language :: Python :: 3
Classifier: License :: OSI Approved :: Apache Software License
Classifier: Operating System :: OS Independent
Requires-Python: >=3.6
